autodiff30/__init__.py
autodiff30/ad.py
autodiff30/dual.py
autodiff30/functions.py
autodiff30/optimization.py
autodiff30-0.0.6.dist-info/LICENCE
autodiff30-0.0.6.dist-info/METADATA
autodiff30-0.0.6.dist-info/WHEEL
autodiff30-0.0.6.dist-info/top_level.txt
autodiff30-0.0.6.dist-info/RECORD
